solidity_parser/__init__.py
solidity_parser/__main__.py
solidity_parser/parser.py
solidity_parser/solidity_antlr4/SolidityLexer.py
solidity_parser/solidity_antlr4/SolidityListener.py
solidity_parser/solidity_antlr4/SolidityParser.py
solidity_parser/solidity_antlr4/SolidityVisitor.py
solidity_parser/solidity_antlr4/__init__.py
eunsol-0.0.5.dist-info/METADATA
eunsol-0.0.5.dist-info/WHEEL
eunsol-0.0.5.dist-info/top_level.txt
eunsol-0.0.5.dist-info/RECORD
