Metadata-Version: 2.1
Name: eunsol
Version: 0.0.5
Summary: use parse
Home-page: https://github.com/eun0o/python-eunsol/
Author: eunOo
Author-email: eun@hexlant.com
License: MIT
Download-URL: https://github.com/eun0o/python-eunsol/tarball/v0.0.5
Keywords: eun
Platform: UNKNOWN
Requires-Dist: antlr4-python3-runtime
